thumbor_icon_handler/__init__.py
thumbor_icon_handler/handler.py
thumbor_icon_handler/icon.py
thumbor_icon_handler-0.0.4.dist-info/LICENSE
thumbor_icon_handler-0.0.4.dist-info/METADATA
thumbor_icon_handler-0.0.4.dist-info/WHEEL
thumbor_icon_handler-0.0.4.dist-info/top_level.txt
thumbor_icon_handler-0.0.4.dist-info/RECORD
