Metadata-Version: 2.1
Name: thumbor-icon-handler
Version: 0.0.4
Summary: Thumbor add serve request for favicon.ico handler.
Home-page: https://github.com/jjonline/thumbor-icon-handler
Author: Jea Yang
Author-email: jjonline@jjonline.cn
Maintainer: Jea Yang
Maintainer-email: jjonline@jjonline.cn
License: Apache-2.0 license
Keywords: thumbor,icon,favicon.ico,imaging,thumbnail,imagemagick
Platform: UNKNOWN
Classifier: Development Status :: 4 - Beta
Classifier: Intended Audience :: Developers
Classifier: Natural Language :: English
Classifier: Operating System :: OS Independent
Classifier: Programming Language :: Python
Classifier: Programming Language :: Python :: 3.7
Classifier: Programming Language :: Python :: 3.8
Classifier: Programming Language :: Python :: 3.9
Classifier: Programming Language :: Python :: 3.10
Classifier: Programming Language :: Python :: Implementation :: CPython
Classifier: Programming Language :: Python :: Implementation :: PyPy
Classifier: Topic :: Software Development :: Libraries :: Python Modules
Requires-Python: >=3.7
License-File: LICENSE
Requires-Dist: thumbor (>=7.0.1)
